matplotalt/__init__.py
matplotalt/alttextify_notebook.py
matplotalt/api_helpers.py
matplotalt/chart_descriptions.py
matplotalt/matplotalt.py
matplotalt/matplotalt_constants.py
matplotalt/matplotalt_helpers.py
matplotalt/setup.py
matplotalt/stat_helpers.py
matplotalt/trend_helpers.py
matplotalt-0.0.6.dist-info/METADATA
matplotalt-0.0.6.dist-info/WHEEL
matplotalt-0.0.6.dist-info/entry_points.txt
matplotalt-0.0.6.dist-info/licenses/LICENSE
matplotalt-0.0.6.dist-info/RECORD
