Metadata-Version: 2.4
Name: matplotalt
Version: 0.0.6
Summary: A package for adding alt text to matplotlib figures in computational notebooks
Project-URL: Homepage, https://github.com/KaiNylund/matplotalt
Project-URL: Documentation, https://matplotalt.readthedocs.io/en/latest/
Project-URL: Discussions, https://github.com/KaiNylund/matplotalt/discussions
Project-URL: Issues, https://github.com/KaiNylund/matplotalt/issues
Author-email: Kai Nylund <knylund@cs.washington.com>, Venkatesh Potluri <potluriv@umich.edu>
Maintainer-email: Kai Nylund <knylund@cs.washington.com>
License-File: LICENSE
Keywords: IPython,Jupyter,LLMs,alt text,matplotlib,seaborn
Classifier: License :: OSI Approved :: MIT License
Classifier: Operating System :: OS Independent
Classifier: Programming Language :: Python :: 3
Requires-Python: >=3.8
Requires-Dist: ipython
Requires-Dist: matplotlib
Requires-Dist: nbconvert
Requires-Dist: nbformat
Requires-Dist: numpy
Requires-Dist: openai
Requires-Dist: pillow
Requires-Dist: python-dateutil
Requires-Dist: scipy
Requires-Dist: seaborn
Requires-Dist: torch
Requires-Dist: transformers>=4
